MANIFEST.in
README.md
setup.py
nict.egg-info/PKG-INFO
nict.egg-info/SOURCES.txt
nict.egg-info/dependency_links.txt
nict.egg-info/top_level.txt
nictemp/.gitignore
nictemp/kimi-cli/.gitignore
nictemp/kimi-cli/.pre-commit-config.yaml
nictemp/kimi-cli/.python-version
nictemp/kimi-cli/AGENTS.md
nictemp/kimi-cli/CHANGELOG.md
nictemp/kimi-cli/CONTRIBUTING.md
nictemp/kimi-cli/Dockerfile
nictemp/kimi-cli/LICENSE
nictemp/kimi-cli/Makefile
nictemp/kimi-cli/NOTICE
nictemp/kimi-cli/README.md
nictemp/kimi-cli/flake.lock
nictemp/kimi-cli/flake.nix
nictemp/kimi-cli/kimi.spec
nictemp/kimi-cli/pyproject.toml
nictemp/kimi-cli/pytest.ini
nictemp/kimi-cli/uv.lock
nictemp/kimi-cli/.agents/skills/gen-changelog/SKILL.md
nictemp/kimi-cli/.agents/skills/gen-docs/SKILL.md
nictemp/kimi-cli/.agents/skills/pull-request/SKILL.md
nictemp/kimi-cli/.agents/skills/release/SKILL.md
nictemp/kimi-cli/.agents/skills/translate-docs/SKILL.md
nictemp/kimi-cli/.github/dependabot.yml
nictemp/kimi-cli/.github/pr-title-checker-config.json
nictemp/kimi-cli/.github/pull_request_template.md
nictemp/kimi-cli/.github/ISSUE_TEMPLATE/1-bug-report.yml
nictemp/kimi-cli/.github/ISSUE_TEMPLATE/2-feature-request.yml
nictemp/kimi-cli/.github/ISSUE_TEMPLATE/config.yml
nictemp/kimi-cli/.github/actions/macos-code-sign/action.yml
nictemp/kimi-cli/.github/workflows/ci-docs.yml
nictemp/kimi-cli/.github/workflows/ci-kimi-cli.yml
nictemp/kimi-cli/.github/workflows/ci-kimi-sdk.yml
nictemp/kimi-cli/.github/workflows/ci-kosong.yml
nictemp/kimi-cli/.github/workflows/ci-pykaos.yml
nictemp/kimi-cli/.github/workflows/docs-pages.yml
nictemp/kimi-cli/.github/workflows/pr-title-checker.yml
nictemp/kimi-cli/.github/workflows/release-kimi-cli.yml
nictemp/kimi-cli/.github/workflows/release-kimi-sdk.yml
nictemp/kimi-cli/.github/workflows/release-kosong.yml
nictemp/kimi-cli/.github/workflows/release-pykaos.yml
nictemp/kimi-cli/.github/workflows/translator.yml
nictemp/kimi-cli/.github/workflows/typos.yml
nictemp/kimi-cli/dist/.gitignore
nictemp/kimi-cli/dist/kimi_cli-0.83-py3-none-any.whl
nictemp/kimi-cli/dist/kimi_cli-0.83.tar.gz
