Metadata-Version: 2.1
Name: nict
Version: 0.3.7
Summary: magicmind examples, An easy to use library to speed up computation (by parallelizing on multi CPUs).
Home-page: 
Author: NICHOLAS WU
Author-email: nicholas_wu@aliyun.com
License: MIT
Requires-Python: >=3.5
